vina2vi/__init__.py
vina2vi/util.py
vina2vi-0.0.13.dist-info/LICENSE
vina2vi-0.0.13.dist-info/METADATA
vina2vi-0.0.13.dist-info/WHEEL
vina2vi-0.0.13.dist-info/top_level.txt
vina2vi-0.0.13.dist-info/RECORD
