Metadata-Version: 2.1
Name: vina2vi
Version: 0.0.13
License: MIT
License-File: LICENSE
Requires-Dist: Unidecode ==1.3.6
Requires-Dist: torch ==1.11.0
Requires-Dist: rapidfuzz ==3.2.0
Requires-Dist: datasets ==2.13.0
Requires-Dist: tokenizers ==0.13.2
Requires-Dist: tensorflow ==2.13.0
Requires-Dist: tensorflow-text ==2.13.0
Requires-Dist: tqdm ==4.66.1
Requires-Dist: pandas ==2.1.0
Requires-Dist: matplotlib ==3.8.0
Requires-Dist: huggingface-hub ==0.17.2
